INSTALL
LICENSE
README
dev.cfg
prod.cfg
push.conf
pusher.py
setup.py
tasty_start.py
Tasty.egg-info/PKG-INFO
Tasty.egg-info/SOURCES.txt
Tasty.egg-info/not-zip-safe
Tasty.egg-info/requires.txt
Tasty.egg-info/sqlobject.txt
Tasty.egg-info/top_level.txt
tasty/__init__.py
tasty/controllers.py
tasty/dimension.py
tasty/helpers.py
tasty/model.py
tasty/templates/__init__.py
tasty/templates/master.kid
tasty/templates/welcome.kid
test/__init__.py
test/test_controllers.py
test/test_model.py
