Metadata-Version: 1.0
Name: Tasty
Version: 1.0.1
Summary: rich, general purpose tagging engine built as a REST service
Home-page: http://tasty.python-hosting.com/
Author: Anders Pearson
Author-email: anders@columbia.edu
License: http://www.gnu.org/licenses/gpl.html
Platform: any
Classifier: Development Status :: 5 - Production/Stable
Classifier: Environment :: Web Environment
Classifier: Intended Audience :: Developers
Classifier: License :: OSI Approved :: GNU General Public License (GPL)
Classifier: Operating System :: OS Independent
Classifier: Topic :: Internet :: WWW/HTTP
Classifier: Topic :: Internet :: WWW/HTTP :: Dynamic Content 
